snakeless_provider_gcloud/__init__.py
snakeless_provider_gcloud/constants.py
snakeless_provider_gcloud/provider.py
snakeless_provider_gcloud/schema.py
snakeless_provider_gcloud/utils.py
snakeless_provider_gcloud-0.2.1.dist-info/entry_points.txt
snakeless_provider_gcloud-0.2.1.dist-info/WHEEL
snakeless_provider_gcloud-0.2.1.dist-info/METADATA
snakeless_provider_gcloud-0.2.1.dist-info/RECORD
