Metadata-Version: 2.1
Name: snakeless-provider-gcloud
Version: 0.2.1
Summary: 
Home-page: UNKNOWN
License: UNKNOWN
Author: German Ivanov
Author-email: germivanov@gmail.com
Requires-Python: >=3.7,<4.0
Classifier: Programming Language :: Python :: 3
Classifier: Programming Language :: Python :: 3.7
Requires-Dist: fs (>=2.1,<3.0)
Requires-Dist: google-auth (>=1.5,<2.0)
Requires-Dist: requests (>=2.20,<3.0)
